rlabs_mini_cache/__init__.py
rlabs_mini_cache/backend/__init__.py
rlabs_mini_cache/backend/base.py
rlabs_mini_cache/backend/file.py
rlabs_mini_cache/backend/memory.py
rlabs_mini_cache/backend/mongodb.py
rlabs_mini_cache/backend/utils/__init__.py
rlabs_mini_cache/backend/utils/encoder.py
rlabs_mini_cache/backend/utils/timestamp.py
rlabs_mini_cache/backend/utils/validate.py
rlabs_mini_cache/cache.py
rlabs_mini_cache/checks.py
rlabs_mini_cache/config.py
rlabs_mini_cache/directory.py
rlabs_mini_cache/error.py
rlabs_mini_cache/logger.py
rlabs_mini_cache/manual_test_run.py
rlabs_mini_cache/py.typed
rlabs_mini_cache/types.py
rlabs_mini_cache-1.0.3.dist-info/METADATA
rlabs_mini_cache-1.0.3.dist-info/WHEEL
rlabs_mini_cache-1.0.3.dist-info/entry_points.txt
rlabs_mini_cache-1.0.3.dist-info/RECORD
